dynamofl/Datasource.py
dynamofl/Helpers.py
dynamofl/MessageHandler.py
dynamofl/Project.py
dynamofl/Request.py
dynamofl/State.py
dynamofl/__init__.py
dynamofl/compatibility_engine.py
dynamofl/logging.py
dynamofl/src.py
dynamofl/vector_db.py
dynamofl/api/DatasourceAPI.py
dynamofl/api/ProjectAPI.py
dynamofl/api/__init__.py
dynamofl/api/billing.py
dynamofl/api/custom_rag_app.py
dynamofl/api/test_custom_rag_app.py
dynamofl/attacks/__init__.py
dynamofl/attacks/attack.py
dynamofl/attacks/pii_extraction.py
dynamofl/auth_data/__init__.py
dynamofl/auth_data/auth_data.py
dynamofl/datasets/__init__.py
dynamofl/datasets/base_dataset.py
dynamofl/datasets/dataset.py
dynamofl/datasets/hf_dataset.py
dynamofl/dynamoguard_streaming/__init__.py
dynamofl/dynamoguard_streaming/client.py
dynamofl/dynamoguard_streaming/streaming_analyze_handler.py
dynamofl/entities/__init__.py
dynamofl/entities/auth_data.py
dynamofl/entities/billing.py
dynamofl/entities/custom_rag_app.py
dynamofl/entities/dataset.py
dynamofl/entities/model.py
dynamofl/entities/test.py
dynamofl/entities/test_custom_rag_app_entities.py
dynamofl/file_transfer/__init__.py
dynamofl/file_transfer/download.py
dynamofl/file_transfer/metadata.py
dynamofl/file_transfer/multipart_file_uploader_api.py
dynamofl/file_transfer/sha.py
dynamofl/file_transfer/thread_executor.py
dynamofl/file_transfer/upload.py
dynamofl/file_transfer/upload_v2.py
dynamofl/models/__init__.py
dynamofl/models/model.py
dynamofl/models/remote_model.py
dynamofl/tests/__init__.py
dynamofl/tests/cpu_config.py
dynamofl/tests/gpu_config.py
dynamofl/tests/test.py
dynamofl-3.0.0.dist-info/METADATA
dynamofl-3.0.0.dist-info/WHEEL
dynamofl-3.0.0.dist-info/top_level.txt
dynamofl-3.0.0.dist-info/RECORD
