Metadata-Version: 2.1
Name: dynamofl
Version: 3.0.0
Author: Emile Indik
Requires-Python: >=3.7
Requires-Dist: requests ~=2.32.0
Requires-Dist: websocket-client ==1.5.0
Requires-Dist: shortuuid ==1.0.11
Requires-Dist: tqdm ==4.66.3
Requires-Dist: dataclasses-json ==0.6.7
